tsg/__init__.py
tsg/client.py
tsg/exc.py
tsg/models.py
tsg/handlers/__init__.py
tsg/handlers/base.py
tsg/handlers/book.py
tsg/handlers/book_common.py
tsg/handlers/browse.py
thestorygraph_client-0.1.6.dist-info/LICENSE
thestorygraph_client-0.1.6.dist-info/METADATA
thestorygraph_client-0.1.6.dist-info/WHEEL
thestorygraph_client-0.1.6.dist-info/top_level.txt
thestorygraph_client-0.1.6.dist-info/RECORD
