Metadata-Version: 2.1
Name: thestorygraph-client
Version: 0.1.6
Summary: A Simple Python Client for TheStoryGraph
Home-page: https://github.com/altvod/thestorygraph-client
Author: Grigory Statsenko
Author-email: grisha100@gmail.com
License: UNKNOWN
Project-URL: Bug Tracker, https://github.com/altvod/thestorygraph-client/issues
Keywords: thestorygraph,books,client
Platform: UNKNOWN
Classifier: Development Status :: 3 - Alpha
Classifier: Intended Audience :: Developers
Classifier: Topic :: Software Development :: Libraries :: Python Modules
Classifier: Programming Language :: Python :: 3
Classifier: Programming Language :: Python :: 3 :: Only
Classifier: Programming Language :: Python :: 3.9
Classifier: Programming Language :: Python :: 3.10
Classifier: License :: OSI Approved :: MIT License
Classifier: Operating System :: OS Independent
Requires-Python: >=3.9
License-File: LICENSE
Requires-Dist: aiohttp
Requires-Dist: attrs
Requires-Dist: beautifulsoup4
Requires-Dist: requests
Requires-Dist: yarl
Provides-Extra: build
Requires-Dist: build ; extra == 'build'
Requires-Dist: twine ; extra == 'build'
Provides-Extra: testing
Requires-Dist: mypy ; extra == 'testing'
Requires-Dist: pytest ; extra == 'testing'
Requires-Dist: types-requests ; extra == 'testing'
